xcstrings_tool/__init__.py
xcstrings_tool/__main__.py
xcstrings_tool/cli.py
xcstrings_tool/core/__init__.py
xcstrings_tool/core/analyzer.py
xcstrings_tool/core/models.py
xcstrings_tool/core/parser.py
xcstrings_tool/reporters/__init__.py
xcstrings_tool/reporters/base.py
xcstrings_tool/reporters/console.py
xcstrings_tool/reporters/csv.py
xcstrings_tool/reporters/json.py
xcstrings_tool/reporters/markdown.py
xcstrings_tool-0.1.0.dist-info/LICENSE
xcstrings_tool-0.1.0.dist-info/METADATA
xcstrings_tool-0.1.0.dist-info/WHEEL
xcstrings_tool-0.1.0.dist-info/entry_points.txt
xcstrings_tool-0.1.0.dist-info/RECORD
