Metadata-Version: 2.1
Name: xcstrings-tool
Version: 0.1.0
Summary: Audit and analyze Xcode String Catalogs (.xcstrings) for localization completeness
Home-page: https://github.com/jaalbin24/xcstrings-tool
License: MIT
Keywords: xcode,localization,i18n,strings,xcstrings,ios,swift
Author: Morgan Olive
Author-email: morgan.olive@example.com
Requires-Python: >=3.9,<4.0
Classifier: Development Status :: 4 - Beta
Classifier: Intended Audience :: Developers
Classifier: License :: OSI Approved :: MIT License
Classifier: Programming Language :: Python :: 3
Classifier: Programming Language :: Python :: 3.9
Classifier: Programming Language :: Python :: 3.10
Classifier: Programming Language :: Python :: 3.11
Classifier: Programming Language :: Python :: 3.12
Classifier: Topic :: Software Development :: Localization
Classifier: Topic :: Software Development :: Quality Assurance
Requires-Dist: click (>=8.0.0,<9.0.0)
Requires-Dist: pydantic (>=2.0.0,<3.0.0)
Requires-Dist: rich (>=13.0.0,<14.0.0)
Project-URL: Repository, https://github.com/jaalbin24/xcstrings-tool
